[ {
  "team_id" : 217,
  "team_name" : "Barcelona",
  "lineup" : [ {
    "player_id" : 4320,
    "player_name" : "Neymar da Silva Santos Junior",
    "player_nickname" : "Neymar",
    "jersey_number" : 11,
    "country" : {
      "id" : 31,
      "name" : "Brazil"
    }
  }, {
    "player_id" : 5203,
    "player_name" : "Sergio Busquets i Burgos",
    "player_nickname" : "Sergio Busquets",
    "jersey_number" : 5,
    "country" : {
      "id" : 214,
      "name" : "Spain"
    }
  }, {
    "player_id" : 5211,
    "player_name" : "Jordi Alba Ramos",
    "player_nickname" : "Jordi Alba",
    "jersey_number" : 18,
    "country" : {
      "id" : 214,
      "name" : "Spain"
    }
  }, {
    "player_id" : 5213,
    "player_name" : "Gerard Piqué Bernabéu",
    "player_nickname" : "Gerard Piqué",
    "jersey_number" : 3,
    "country" : {
      "id" : 214,
      "name" : "Spain"
    }
  }, {
    "player_id" : 5216,
    "player_name" : "Andrés Iniesta Luján",
    "player_nickname" : "Andrés Iniesta",
    "jersey_number" : 8,
    "country" : {
      "id" : 214,
      "name" : "Spain"
    }
  }, {
    "player_id" : 5246,
    "player_name" : "Luis Alberto Suárez Díaz",
    "player_nickname" : "Luis Suárez",
    "jersey_number" : 9,
    "country" : {
      "id" : 242,
      "name" : "Uruguay"
    }
  }, {
    "player_id" : 5470,
    "player_name" : "Ivan Rakitić",
    "player_nickname" : null,
    "jersey_number" : 4,
    "country" : {
      "id" : 56,
      "name" : "Croatia"
    }
  }, {
    "player_id" : 5492,
    "player_name" : "Samuel Yves Umtiti",
    "player_nickname" : "Samuel Umtiti",
    "jersey_number" : 23,
    "country" : {
      "id" : 78,
      "name" : "France"
    }
  }, {
    "player_id" : 5503,
    "player_name" : "Lionel Andrés Messi Cuccittini",
    "player_nickname" : "Lionel Messi",
    "jersey_number" : 10,
    "country" : {
      "id" : 11,
      "name" : "Argentina"
    }
  }, {
    "player_id" : 5506,
    "player_name" : "Javier Alejandro Mascherano",
    "player_nickname" : "Javier Mascherano",
    "jersey_number" : 14,
    "country" : {
      "id" : 11,
      "name" : "Argentina"
    }
  }, {
    "player_id" : 6379,
    "player_name" : "Sergi Roberto Carnicer",
    "player_nickname" : "Sergi Roberto",
    "jersey_number" : 20,
    "country" : {
      "id" : 214,
      "name" : "Spain"
    }
  }, {
    "player_id" : 6849,
    "player_name" : "Lucas Digne",
    "player_nickname" : null,
    "jersey_number" : 19,
    "country" : {
      "id" : 78,
      "name" : "France"
    }
  }, {
    "player_id" : 10802,
    "player_name" : "André Filipe Tavares Gomes",
    "player_nickname" : "André Gomes",
    "jersey_number" : 21,
    "country" : {
      "id" : 183,
      "name" : "Portugal"
    }
  }, {
    "player_id" : 20055,
    "player_name" : "Marc-André ter Stegen",
    "player_nickname" : "Marc-André ter Stegen",
    "jersey_number" : 1,
    "country" : {
      "id" : 85,
      "name" : "Germany"
    }
  } ]
}, {
  "team_id" : 222,
  "team_name" : "Villarreal",
  "lineup" : [ {
    "player_id" : 6357,
    "player_name" : "Jonathan dos Santos Ramírez",
    "player_nickname" : "Jonathan dos Santos",
    "jersey_number" : 8,
    "country" : {
      "id" : 147,
      "name" : "Mexico"
    }
  }, {
    "player_id" : 6735,
    "player_name" : "Adrián López Álvarez",
    "player_nickname" : "Adrián López",
    "jersey_number" : 15,
    "country" : {
      "id" : 214,
      "name" : "Spain"
    }
  }, {
    "player_id" : 6759,
    "player_name" : "Roberto Soriano",
    "player_nickname" : null,
    "jersey_number" : 20,
    "country" : {
      "id" : 112,
      "name" : "Italy"
    }
  }, {
    "player_id" : 6762,
    "player_name" : "Álvaro González Soberón",
    "player_nickname" : "Álvaro González",
    "jersey_number" : 12,
    "country" : {
      "id" : 214,
      "name" : "Spain"
    }
  }, {
    "player_id" : 6765,
    "player_name" : "Rodrigo Hernández Cascante",
    "player_nickname" : "Rodri Hernández",
    "jersey_number" : 16,
    "country" : {
      "id" : 214,
      "name" : "Spain"
    }
  }, {
    "player_id" : 6771,
    "player_name" : "Manuel Trigueros Muñoz",
    "player_nickname" : "Manu Trigueros",
    "jersey_number" : 14,
    "country" : {
      "id" : 214,
      "name" : "Spain"
    }
  }, {
    "player_id" : 6772,
    "player_name" : "Mario Gaspar Pérez Martínez",
    "player_nickname" : "Mario Gaspar",
    "jersey_number" : 2,
    "country" : {
      "id" : 214,
      "name" : "Spain"
    }
  }, {
    "player_id" : 6828,
    "player_name" : "Jaume Vicent Costa Jordá",
    "player_nickname" : "Jaume Costa",
    "jersey_number" : 11,
    "country" : {
      "id" : 214,
      "name" : "Spain"
    }
  }, {
    "player_id" : 6829,
    "player_name" : "Samuel Castillejo Azuaga",
    "player_nickname" : "Samu Castillejo",
    "jersey_number" : 19,
    "country" : {
      "id" : 214,
      "name" : "Spain"
    }
  }, {
    "player_id" : 6859,
    "player_name" : "Nicola Sansone",
    "player_nickname" : null,
    "jersey_number" : 18,
    "country" : {
      "id" : 112,
      "name" : "Italy"
    }
  }, {
    "player_id" : 6862,
    "player_name" : "Cédric Bakambu",
    "player_nickname" : null,
    "jersey_number" : 17,
    "country" : {
      "id" : 52,
      "name" : "Congo, (Kinshasa)"
    }
  }, {
    "player_id" : 7034,
    "player_name" : "Mateo Pablo Musacchio",
    "player_nickname" : "Mateo Musacchio",
    "jersey_number" : 5,
    "country" : {
      "id" : 11,
      "name" : "Argentina"
    }
  }, {
    "player_id" : 8697,
    "player_name" : "Andrés Eduardo Fernández Moreno",
    "player_nickname" : "Andrés Fernández",
    "jersey_number" : 13,
    "country" : {
      "id" : 214,
      "name" : "Spain"
    }
  }, {
    "player_id" : 26009,
    "player_name" : "Roberto Soldado Rillo",
    "player_nickname" : "Roberto Soldado",
    "jersey_number" : 9,
    "country" : {
      "id" : 214,
      "name" : "Spain"
    }
  } ]
} ]