[ {
  "team_id" : 217,
  "team_name" : "Barcelona",
  "lineup" : [ {
    "player_id" : 4320,
    "player_name" : "Neymar da Silva Santos Junior",
    "player_nickname" : "Neymar",
    "jersey_number" : 11,
    "country" : {
      "id" : 31,
      "name" : "Brazil"
    }
  }, {
    "player_id" : 4324,
    "player_name" : "Daniel Alves da Silva",
    "player_nickname" : "Dani Alves",
    "jersey_number" : 6,
    "country" : {
      "id" : 31,
      "name" : "Brazil"
    }
  }, {
    "player_id" : 4691,
    "player_name" : "Claudio Andrés Bravo Muñoz",
    "player_nickname" : "Claudio Bravo",
    "jersey_number" : 13,
    "country" : {
      "id" : 45,
      "name" : "Chile"
    }
  }, {
    "player_id" : 5203,
    "player_name" : "Sergio Busquets i Burgos",
    "player_nickname" : "Sergio Busquets",
    "jersey_number" : 16,
    "country" : {
      "id" : 214,
      "name" : "Spain"
    }
  }, {
    "player_id" : 5211,
    "player_name" : "Jordi Alba Ramos",
    "player_nickname" : "Jordi Alba",
    "jersey_number" : 18,
    "country" : {
      "id" : 214,
      "name" : "Spain"
    }
  }, {
    "player_id" : 5213,
    "player_name" : "Gerard Piqué Bernabéu",
    "player_nickname" : "Gerard Piqué",
    "jersey_number" : 3,
    "country" : {
      "id" : 214,
      "name" : "Spain"
    }
  }, {
    "player_id" : 5216,
    "player_name" : "Andrés Iniesta Luján",
    "player_nickname" : "Andrés Iniesta",
    "jersey_number" : 8,
    "country" : {
      "id" : 214,
      "name" : "Spain"
    }
  }, {
    "player_id" : 5246,
    "player_name" : "Luis Alberto Suárez Díaz",
    "player_nickname" : "Luis Suárez",
    "jersey_number" : 9,
    "country" : {
      "id" : 242,
      "name" : "Uruguay"
    }
  }, {
    "player_id" : 5470,
    "player_name" : "Ivan Rakitić",
    "player_nickname" : null,
    "jersey_number" : 4,
    "country" : {
      "id" : 56,
      "name" : "Croatia"
    }
  }, {
    "player_id" : 5503,
    "player_name" : "Lionel Andrés Messi Cuccittini",
    "player_nickname" : "Lionel Messi",
    "jersey_number" : 10,
    "country" : {
      "id" : 11,
      "name" : "Argentina"
    }
  }, {
    "player_id" : 5506,
    "player_name" : "Javier Alejandro Mascherano",
    "player_nickname" : "Javier Mascherano",
    "jersey_number" : 14,
    "country" : {
      "id" : 11,
      "name" : "Argentina"
    }
  }, {
    "player_id" : 6379,
    "player_name" : "Sergi Roberto Carnicer",
    "player_nickname" : "Sergi Roberto",
    "jersey_number" : 24,
    "country" : {
      "id" : 214,
      "name" : "Spain"
    }
  }, {
    "player_id" : 11094,
    "player_name" : "Arda Turan",
    "player_nickname" : null,
    "jersey_number" : 7,
    "country" : {
      "id" : 233,
      "name" : "Turkey"
    }
  } ]
}, {
  "team_id" : 212,
  "team_name" : "Atlético Madrid",
  "lineup" : [ {
    "player_id" : 4788,
    "player_name" : "Jesús Gámez Duarte",
    "player_nickname" : "Jesús Gámez",
    "jersey_number" : 18,
    "country" : {
      "id" : 214,
      "name" : "Spain"
    }
  }, {
    "player_id" : 5199,
    "player_name" : "Jorge Resurrección Merodio",
    "player_nickname" : "Koke",
    "jersey_number" : 6,
    "country" : {
      "id" : 214,
      "name" : "Spain"
    }
  }, {
    "player_id" : 5249,
    "player_name" : "Diego Roberto Godín Leal",
    "player_nickname" : "Diego Godín",
    "jersey_number" : 2,
    "country" : {
      "id" : 242,
      "name" : "Uruguay"
    }
  }, {
    "player_id" : 5259,
    "player_name" : "José María Giménez de Vargas",
    "player_nickname" : "José Giménez",
    "jersey_number" : 24,
    "country" : {
      "id" : 242,
      "name" : "Uruguay"
    }
  }, {
    "player_id" : 5487,
    "player_name" : "Antoine Griezmann",
    "player_nickname" : null,
    "jersey_number" : 7,
    "country" : {
      "id" : 78,
      "name" : "France"
    }
  }, {
    "player_id" : 5633,
    "player_name" : "Yannick Ferreira Carrasco",
    "player_nickname" : "Yannick Carrasco",
    "jersey_number" : 21,
    "country" : {
      "id" : 22,
      "name" : "Belgium"
    }
  }, {
    "player_id" : 6320,
    "player_name" : "Filipe Luis Kasmirski",
    "player_nickname" : "Filipe Luis",
    "jersey_number" : 3,
    "country" : {
      "id" : 31,
      "name" : "Brazil"
    }
  }, {
    "player_id" : 6375,
    "player_name" : "Juan Francisco Torres Belén",
    "player_nickname" : "Juanfran",
    "jersey_number" : 20,
    "country" : {
      "id" : 214,
      "name" : "Spain"
    }
  }, {
    "player_id" : 6376,
    "player_name" : "Stefan Savić",
    "player_nickname" : null,
    "jersey_number" : 15,
    "country" : {
      "id" : 152,
      "name" : "Montenegro"
    }
  }, {
    "player_id" : 6378,
    "player_name" : "Jan Oblak",
    "player_nickname" : null,
    "jersey_number" : 13,
    "country" : {
      "id" : 208,
      "name" : "Slovenia"
    }
  }, {
    "player_id" : 6381,
    "player_name" : "Saúl Ñíguez Esclapez",
    "player_nickname" : "Saúl Ñíguez",
    "jersey_number" : 17,
    "country" : {
      "id" : 214,
      "name" : "Spain"
    }
  }, {
    "player_id" : 6383,
    "player_name" : "Thomas Teye Partey",
    "player_nickname" : "Thomas Partey",
    "jersey_number" : 22,
    "country" : {
      "id" : 86,
      "name" : "Ghana"
    }
  }, {
    "player_id" : 6384,
    "player_name" : "Gabriel Fernández Arenas",
    "player_nickname" : "Gabi",
    "jersey_number" : 14,
    "country" : {
      "id" : 214,
      "name" : "Spain"
    }
  }, {
    "player_id" : 19668,
    "player_name" : "Augusto Matías Fernández",
    "player_nickname" : "Augusto Fernández",
    "jersey_number" : 12,
    "country" : {
      "id" : 11,
      "name" : "Argentina"
    }
  } ]
} ]