[ {
  "team_id" : 1212,
  "team_name" : "Jamaica Women's",
  "lineup" : [ {
    "player_id" : 4945,
    "player_name" : "Havana Solaun",
    "player_nickname" : null,
    "jersey_number" : 6,
    "country" : {
      "id" : 241,
      "name" : "United States of America"
    }
  }, {
    "player_id" : 25535,
    "player_name" : "Tiffany Cameron",
    "player_nickname" : null,
    "jersey_number" : 15,
    "country" : {
      "id" : 113,
      "name" : "Jamaica"
    }
  }, {
    "player_id" : 25538,
    "player_name" : "Jody Brown",
    "player_nickname" : null,
    "jersey_number" : 10,
    "country" : {
      "id" : 113,
      "name" : "Jamaica"
    }
  }, {
    "player_id" : 25545,
    "player_name" : "Allyson Swaby",
    "player_nickname" : null,
    "jersey_number" : 17,
    "country" : {
      "id" : 113,
      "name" : "Jamaica"
    }
  }, {
    "player_id" : 25546,
    "player_name" : "Cheyna Matthews",
    "player_nickname" : null,
    "jersey_number" : 20,
    "country" : {
      "id" : 113,
      "name" : "Jamaica"
    }
  }, {
    "player_id" : 25548,
    "player_name" : "Konya Plummer",
    "player_nickname" : null,
    "jersey_number" : 5,
    "country" : {
      "id" : 113,
      "name" : "Jamaica"
    }
  }, {
    "player_id" : 25553,
    "player_name" : "Trudi Sudan Carter",
    "player_nickname" : null,
    "jersey_number" : 18,
    "country" : {
      "id" : 113,
      "name" : "Jamaica"
    }
  }, {
    "player_id" : 25554,
    "player_name" : "Khadija Monifa Shaw",
    "player_nickname" : null,
    "jersey_number" : 11,
    "country" : {
      "id" : 113,
      "name" : "Jamaica"
    }
  }, {
    "player_id" : 25557,
    "player_name" : "Deneisha Selena Blackwood",
    "player_nickname" : null,
    "jersey_number" : 14,
    "country" : {
      "id" : 113,
      "name" : "Jamaica"
    }
  }, {
    "player_id" : 25558,
    "player_name" : "Chantelle Swaby",
    "player_nickname" : null,
    "jersey_number" : 4,
    "country" : {
      "id" : 113,
      "name" : "Jamaica"
    }
  }, {
    "player_id" : 25771,
    "player_name" : "Sashana Campbell",
    "player_nickname" : null,
    "jersey_number" : 12,
    "country" : {
      "id" : 113,
      "name" : "Jamaica"
    }
  }, {
    "player_id" : 25772,
    "player_name" : "Mireya Grey",
    "player_nickname" : null,
    "jersey_number" : 22,
    "country" : {
      "id" : 113,
      "name" : "Jamaica"
    }
  }, {
    "player_id" : 25851,
    "player_name" : "Nicole McClure",
    "player_nickname" : null,
    "jersey_number" : 13,
    "country" : {
      "id" : 113,
      "name" : "Jamaica"
    }
  }, {
    "player_id" : 25852,
    "player_name" : "Toriana Jade Patterson",
    "player_nickname" : null,
    "jersey_number" : 19,
    "country" : {
      "id" : 113,
      "name" : "Jamaica"
    }
  } ]
}, {
  "team_id" : 1205,
  "team_name" : "Australia Women's",
  "lineup" : [ {
    "player_id" : 4961,
    "player_name" : "Samantha Kerr",
    "player_nickname" : null,
    "jersey_number" : 20,
    "country" : {
      "id" : 14,
      "name" : "Australia"
    }
  }, {
    "player_id" : 4979,
    "player_name" : "Katrina Gorry",
    "player_nickname" : null,
    "jersey_number" : 19,
    "country" : {
      "id" : 14,
      "name" : "Australia"
    }
  }, {
    "player_id" : 5000,
    "player_name" : "Steph Catley",
    "player_nickname" : null,
    "jersey_number" : 7,
    "country" : {
      "id" : 14,
      "name" : "Australia"
    }
  }, {
    "player_id" : 5066,
    "player_name" : "Lydia Williams",
    "player_nickname" : null,
    "jersey_number" : 1,
    "country" : {
      "id" : 14,
      "name" : "Australia"
    }
  }, {
    "player_id" : 5076,
    "player_name" : "Emily van Egmond",
    "player_nickname" : null,
    "jersey_number" : 10,
    "country" : {
      "id" : 14,
      "name" : "Australia"
    }
  }, {
    "player_id" : 5078,
    "player_name" : "Alanna Kennedy",
    "player_nickname" : null,
    "jersey_number" : 14,
    "country" : {
      "id" : 14,
      "name" : "Australia"
    }
  }, {
    "player_id" : 5095,
    "player_name" : "Ellie Carpenter",
    "player_nickname" : null,
    "jersey_number" : 21,
    "country" : {
      "id" : 14,
      "name" : "Australia"
    }
  }, {
    "player_id" : 6818,
    "player_name" : "Hayley Raso",
    "player_nickname" : null,
    "jersey_number" : 16,
    "country" : {
      "id" : 14,
      "name" : "Australia"
    }
  }, {
    "player_id" : 11338,
    "player_name" : "Caitlin Foord",
    "player_nickname" : null,
    "jersey_number" : 9,
    "country" : {
      "id" : 14,
      "name" : "Australia"
    }
  }, {
    "player_id" : 25539,
    "player_name" : "Lisa De Vanna",
    "player_nickname" : null,
    "jersey_number" : 11,
    "country" : {
      "id" : 14,
      "name" : "Australia"
    }
  }, {
    "player_id" : 25547,
    "player_name" : "Chloe Logarzo",
    "player_nickname" : null,
    "jersey_number" : 6,
    "country" : {
      "id" : 14,
      "name" : "Australia"
    }
  }, {
    "player_id" : 25742,
    "player_name" : "Karly Roestbakken",
    "player_nickname" : null,
    "jersey_number" : 5,
    "country" : {
      "id" : 14,
      "name" : "Australia"
    }
  }, {
    "player_id" : 25744,
    "player_name" : "Emily Gielnik",
    "player_nickname" : null,
    "jersey_number" : 15,
    "country" : {
      "id" : 14,
      "name" : "Australia"
    }
  }, {
    "player_id" : 25850,
    "player_name" : "Aivi Belinda Kerstin Luik",
    "player_nickname" : null,
    "jersey_number" : 3,
    "country" : {
      "id" : 14,
      "name" : "Australia"
    }
  } ]
} ]